generic_paths/__init__.py
generic_paths/_common.py
generic_paths/bfs.py
generic_paths-0.0.3.dist-info/METADATA
generic_paths-0.0.3.dist-info/RECORD
generic_paths-0.0.3.dist-info/WHEEL
generic_paths-0.0.3.dist-info/top_level.txt
